bot_safe_agents/__init__.py
bot_safe_agents/bot_safe_agents.py
bot_safe_agents/user_agents.txt
bot_safe_agents-1.1.dist-info/METADATA
bot_safe_agents-1.1.dist-info/WHEEL
bot_safe_agents-1.1.dist-info/top_level.txt
bot_safe_agents-1.1.dist-info/RECORD
