Metadata-Version: 2.4
Name: bot-safe-agents
Version: 1.1
Summary: A library for fetching a list of bot-safe user agents.
Author: Ivan Sincek
Project-URL: Homepage, https://github.com/ivan-sincek/bot-safe-agents
Classifier: Programming Language :: Python :: 3
Classifier: License :: OSI Approved :: MIT License
Classifier: Operating System :: OS Independent
Requires-Python: >=3.8
